eclipsescraper
