Metadata-Version: 1.1
Name: eclipsescraper
Version: 0.3
Summary: Python module for scraping NASA's eclipse site into usable CZML documents
Home-page: https://github.com/Frencil/eclipsescraper
Author: Christopher Clark (Frencil)
Author-email: frencils@gmail.com
License: Apache 2.0
Keywords: GIS JSON CZML Cesium Globe Eclipse NASA
Platform: UNKNOWN
Classifier: Topic :: Scientific/Engineering :: GIS
Classifier: Programming Language :: Python
Classifier: Programming Language :: Python :: 3.3
Classifier: Intended Audience :: Developers
Classifier: License :: OSI Approved :: Apache Software License
Classifier: Operating System :: OS Independent
